COPYING
MANIFEST.in
README
health_ntd_dengue_view.xml
setup.py
./__init__.py
./health_ntd_dengue.py
./health_ntd_dengue_view.xml
./tryton.cfg
./data/health_ntd_dengue_sequence.xml
./data/lab_test_data.xml
./doc/index.rst
./locale/ar.po
./locale/de.po
./locale/el.po
./locale/es.po
./locale/fr.po
./locale/it_IT.po
./locale/ja_JP.po
./locale/lo.po
./locale/pt_BR.po
./locale/zh_CN.po
./tests/__init__.py
./tests/test_health_ntd_dengue.py
./view/gnuhealth_dengue_du_survey_form.xml
./view/gnuhealth_dengue_du_survey_tree.xml
data/health_ntd_dengue_sequence.xml
data/lab_test_data.xml
locale/ar.po
locale/de.po
locale/el.po
locale/es.po
locale/fr.po
locale/it_IT.po
locale/ja_JP.po
locale/lo.po
locale/pt_BR.po
locale/zh_CN.po
trytond_health_ntd_dengue.egg-info/PKG-INFO
trytond_health_ntd_dengue.egg-info/SOURCES.txt
trytond_health_ntd_dengue.egg-info/dependency_links.txt
trytond_health_ntd_dengue.egg-info/entry_points.txt
trytond_health_ntd_dengue.egg-info/not-zip-safe
trytond_health_ntd_dengue.egg-info/requires.txt
trytond_health_ntd_dengue.egg-info/top_level.txt
view/gnuhealth_dengue_du_survey_form.xml
view/gnuhealth_dengue_du_survey_tree.xml